file_managers/__init__.py
file_managers-0.24.0.dist-info/METADATA
file_managers-0.24.0.dist-info/WHEEL
file_managers-0.24.0.dist-info/top_level.txt
file_managers-0.24.0.dist-info/RECORD
