Metadata-Version: 2.1
Name: file-managers
Version: 0.24.0
Summary: A Python Package to manage your files and folders easily in different ways.
Home-page: https://github.com/MusfiqDehan/file-managers
Author: Md. Musfiqur Rahaman
Author-email: musfiqur.rahaman@northsouth.edu
Requires-Dist: twine
Requires-Dist: wheel
